bergamot-0.4.5.dist-info/WHEEL
bergamot-0.4.5.dist-info/RECORD
bergamot-0.4.5.dist-info/METADATA
bergamot-0.4.5.dist-info/LICENSE
bergamot-0.4.5.dist-info/entry_points.txt
bergamot-0.4.5.dist-info/top_level.txt
bergamot/utils.py
bergamot/repository.py
bergamot/__main__.py
bergamot/__init__.py
bergamot/typing_utils.py
bergamot/_bergamot.cpython-38-x86_64-linux-gnu.so
bergamot/cmds.py
